AUTHORS.rst
CHANGES.rst
LICENSE.txt
MANIFEST.in
README.rst
setup.py
Flask_User.egg-info/PKG-INFO
Flask_User.egg-info/SOURCES.txt
Flask_User.egg-info/dependency_links.txt
Flask_User.egg-info/not-zip-safe
Flask_User.egg-info/requires.txt
Flask_User.egg-info/top_level.txt
flask_user/__init__.py
flask_user/access.py
flask_user/db_adapters.py
flask_user/decorators.py
flask_user/emails.py
flask_user/forms.py
flask_user/passwords.py
flask_user/settings.py
flask_user/signals.py
flask_user/tokens.py
flask_user/translations.py
flask_user/views.py
flask_user/templates/base.html
flask_user/templates/flask_user/_macros.html
flask_user/templates/flask_user/change_password.html
flask_user/templates/flask_user/change_username.html
flask_user/templates/flask_user/flask_user_base.html
flask_user/templates/flask_user/forgot_password.html
flask_user/templates/flask_user/invite.html
flask_user/templates/flask_user/login.html
flask_user/templates/flask_user/login_or_register.html
flask_user/templates/flask_user/manage_emails.html
flask_user/templates/flask_user/member_base.html
flask_user/templates/flask_user/public_base.html
flask_user/templates/flask_user/register.html
flask_user/templates/flask_user/resend_confirm_email.html
flask_user/templates/flask_user/reset_password.html
flask_user/templates/flask_user/user_profile.html
flask_user/templates/flask_user/emails/base_message.html
flask_user/templates/flask_user/emails/base_message.txt
flask_user/templates/flask_user/emails/base_subject.txt
flask_user/templates/flask_user/emails/confirm_email_message.html
flask_user/templates/flask_user/emails/confirm_email_message.txt
flask_user/templates/flask_user/emails/confirm_email_subject.txt
flask_user/templates/flask_user/emails/forgot_password_message.html
flask_user/templates/flask_user/emails/forgot_password_message.txt
flask_user/templates/flask_user/emails/forgot_password_subject.txt
flask_user/templates/flask_user/emails/invite_message.html
flask_user/templates/flask_user/emails/invite_message.txt
flask_user/templates/flask_user/emails/invite_subject.txt
flask_user/templates/flask_user/emails/password_changed_message.html
