Metadata-Version: 1.1
Name: Flask-User
Version: 0.6.13
Summary: Customizable User Account Management for Flask: Register, Confirm email, Login, Change username, Change password, Forgot password and more.
Home-page: http://github.com/lingthio/Flask-User
Author: Ling Thio
Author-email: ling.thio@gmail.com
License: BSD License
Keywords: Flask User Registration Email Username Confirmation Password Reset
Platform: any
Classifier: Development Status :: 5 - Production/Stable
Classifier: Environment :: Web Environment
Classifier: Framework :: Flask
Classifier: Intended Audience :: Developers
Classifier: License :: OSI Approved :: BSD License
Classifier: Natural Language :: Chinese (Simplified)
Classifier: Natural Language :: Dutch
Classifier: Natural Language :: English
Classifier: Natural Language :: French
Classifier: Operating System :: OS Independent
Classifier: Programming Language :: Python
Classifier: Programming Language :: Python :: 2.6
Classifier: Programming Language :: Python :: 2.7
Classifier: Programming Language :: Python :: 3.3
Classifier: Programming Language :: Python :: 3.4
Classifier: Programming Language :: Python :: 3.5
Classifier: Programming Language :: Python :: 3.6
Classifier: Topic :: Internet :: WWW/HTTP :: Dynamic Content
Classifier: Topic :: Security
Classifier: Topic :: Software Development :: Libraries :: Python Modules
